rfc9420/__init__.py
rfc9420/api/__init__.py
rfc9420/api/session.py
rfc9420/codec/mls.py
rfc9420/codec/tls.py
rfc9420/crypto/__init__.py
rfc9420/crypto/ciphersuites.py
rfc9420/crypto/crypto_provider.py
rfc9420/crypto/default_crypto_provider.py
rfc9420/crypto/hpke_backend.py
rfc9420/crypto/hpke_labels.py
rfc9420/crypto/labels.py
rfc9420/crypto/utils.py
rfc9420/crypto/x509.py
rfc9420/crypto/x509_policy.py
rfc9420/crypto/x509_revocation.py
rfc9420/extensions/extensions.py
rfc9420/interop/__init__.py
rfc9420/interop/cli.py
rfc9420/interop/harness.py
rfc9420/interop/test_vectors_runner.py
rfc9420/interop/wire.py
rfc9420/mls/exceptions.py
rfc9420/mls/group.py
rfc9420/protocol/__init__.py
rfc9420/protocol/credentials.py
rfc9420/protocol/data_structures.py
rfc9420/protocol/key_packages.py
rfc9420/protocol/key_schedule.py
rfc9420/protocol/messages.py
rfc9420/protocol/mls_group.py
rfc9420/protocol/ratchet_tree.py
rfc9420/protocol/refs.py
rfc9420/protocol/secret_tree.py
rfc9420/protocol/test_vectors.py
rfc9420/protocol/transcripts.py
rfc9420/protocol/tree_math.py
rfc9420/protocol/validations.py
rfc9420-0.3.2.dist-info/METADATA
rfc9420-0.3.2.dist-info/WHEEL
rfc9420-0.3.2.dist-info/entry_points.txt
rfc9420-0.3.2.dist-info/RECORD
