Metadata-Version: 2.4
Name: rfc9420
Version: 0.3.2
Summary: Messaging Layer Security (MLS) protocol implementation (RFC 9420) in Python
Author: rfc9420 maintainers
License: Apache-2.0
Keywords: cryptography,hpke,messaging layer security,mls,rfc9420
Classifier: Development Status :: 3 - Alpha
Classifier: License :: OSI Approved :: Apache Software License
Classifier: Programming Language :: Python :: 3
Classifier: Programming Language :: Python :: 3 :: Only
Classifier: Topic :: Security :: Cryptography
Requires-Python: >=3.9
Requires-Dist: certifi>=2024.7.4
Requires-Dist: cryptography>=42
Requires-Dist: rfc9180>=0.2.0
Provides-Extra: dev
Requires-Dist: mypy>=1.10; extra == 'dev'
Requires-Dist: pytest>=8; extra == 'dev'
Requires-Dist: ruff>=0.6; extra == 'dev'
